onionrouter/__init__.py
onionrouter/config_handlers.py
onionrouter/custom_exceptions.py
onionrouter/lookups.py
onionrouter/msockets.py
onionrouter/olib.py
onionrouter/onionrouter.py
onionrouter/rerouter.py
onionrouter/routers.py
onionrouter/configs/onionrouter.ini
onionrouter-0.5.2.dist-info/DESCRIPTION.rst
onionrouter-0.5.2.dist-info/METADATA
onionrouter-0.5.2.dist-info/RECORD
onionrouter-0.5.2.dist-info/WHEEL
onionrouter-0.5.2.dist-info/entry_points.txt
onionrouter-0.5.2.dist-info/metadata.json
onionrouter-0.5.2.dist-info/top_level.txt
