Metadata-Version: 2.0
Name: onionrouter
Version: 0.5.2
Summary: Python Onion Routed Mail Deliveries
Home-page: https://github.com/ehloonion/onionrouter
Author: Ehlo Onion
Author-email: onionmx@lists.immerda.ch
License: GNU General Public License v3
Keywords: onionrouter
Platform: UNKNOWN
Classifier: Development Status :: 4 - Beta
Classifier: Intended Audience :: Developers
Classifier: License :: OSI Approved :: GNU General Public License v3 (GPLv3)
Classifier: Natural Language :: English
Classifier: Programming Language :: Python :: 2
Classifier: Programming Language :: Python :: 2.7
Classifier: Programming Language :: Python :: 3
Classifier: Programming Language :: Python :: 3.3
Classifier: Programming Language :: Python :: 3.4
Classifier: Programming Language :: Python :: 3.5
Classifier: Programming Language :: Python :: 3.6
Requires-Dist: PyYAML (==4.2b1)
Requires-Dist: dnspython
